voluptuous_errors.py
voluptuous_errors-0.0.dist-info/WHEEL
voluptuous_errors-0.0.dist-info/METADATA
voluptuous_errors-0.0.dist-info/RECORD
