Metadata-Version: 2.1
Name: voluptuous_errors
Version: 0.0
Summary: report voluptuous errors
Requires-Python: >=3.6
Requires-Dist: inform
Requires-Dist: nestedtext>=3.7
Requires-Dist: voluptuous
